nlmdb/__init__.py
nlmdb/_api.py
nlmdb/_private_api.py
nlmdb/_sql_agent.py
nlmdb/_viz_agent.py
nlmdb/config.py
nlmdb/agents/__init__.py
nlmdb/agents/agent_factory.py
nlmdb/database/__init__.py
nlmdb/database/handler.py
nlmdb/database/tools.py
nlmdb/examples/__init__.py
nlmdb/examples/example_queries.py
nlmdb/mcp/__init__.py
nlmdb/mcp/handler.py
nlmdb-1.3.8.dist-info/METADATA
nlmdb-1.3.8.dist-info/WHEEL
nlmdb-1.3.8.dist-info/top_level.txt
nlmdb-1.3.8.dist-info/RECORD
