Metadata-Version: 2.4
Name: nlmdb
Version: 1.3.8
Summary: Natural Language Model Database - Query databases using natural language
Home-page: https://github.com/rakshithdharmap/nlmdb
Author: Rakshith Dharmappa
Author-email: rakshith.officialmail@gmail.com
Project-URL: Bug Tracker, https://github.com/rakshithdharmap/nlmdb/issues
Project-URL: Documentation, https://github.com/rakshithdharmap/nlmdb#readme
Project-URL: Source Code, https://github.com/rakshithdharmap/nlmdb
Keywords: database,natural language,openai,huggingface,sql,privacy,ai,llm,mcp,visualization,plotly
Classifier: Development Status :: 3 - Alpha
Classifier: Intended Audience :: Developers
Classifier: Programming Language :: Python :: 3
Classifier: Programming Language :: Python :: 3.8
Classifier: Programming Language :: Python :: 3.9
Classifier: Programming Language :: Python :: 3.10
Classifier: Programming Language :: Python :: 3.11
Classifier: Topic :: Database
Classifier: Topic :: Scientific/Engineering :: Artificial Intelligence
Classifier: Topic :: Scientific/Engineering :: Visualization
Classifier: License :: OSI Approved :: MIT License
Classifier: Operating System :: OS Independent
Requires-Python: >=3.8
Requires-Dist: openai>=1.0.0
Requires-Dist: langchain>=0.1.0
Requires-Dist: langchain-core>=0.1.0
Requires-Dist: langchain-community>=0.0.0
Requires-Dist: langchain-experimental>=0.0.0
Requires-Dist: langchain-huggingface>=0.0.1
Requires-Dist: timm
Requires-Dist: pandas>=1.0.0
Requires-Dist: plotly>=5.0.0
Dynamic: author
Dynamic: author-email
Dynamic: classifier
Dynamic: description
Dynamic: description-content-type
Dynamic: home-page
Dynamic: keywords
Dynamic: project-url
Dynamic: requires-dist
Dynamic: requires-python
Dynamic: summary
